<?xml version="1.0"?>
<!DOCTYPE hibernate-mapping PUBLIC "-//Hibernate/Hibernate Mapping DTD 3.0//EN"
        "http://hibernate.sourceforge.net/hibernate-mapping-3.0.dtd">

<hibernate-mapping>
    <class name="by.bsu.models.User" table="user" catalog="listenit_db">
        <id name="login" type="string">
            <column name="login" length="128" not-null="true" unique="true" />
        </id>
        <property name="password" type="string">
            <column name="password" length="128" not-null="true" />
        </property>
    </class>
</hibernate-mapping>
